multiranges/__init__.py
multiranges/exceptions.py
multiranges/multiranges.py
multiranges-0.0.2.dist-info/LICENSE
multiranges-0.0.2.dist-info/METADATA
multiranges-0.0.2.dist-info/WHEEL
multiranges-0.0.2.dist-info/top_level.txt
multiranges-0.0.2.dist-info/RECORD
