Metadata-Version: 2.1
Name: multiranges
Version: 0.0.2
Summary: MultiRanges
Home-page: https://gitlab.com/enzoconejero/multiranges.git
Author: Enzo Conejero
Author-email: enzoconejero0@gmail.com
License: UNKNOWN
Platform: UNKNOWN
Classifier: Development Status :: 3 - Alpha
Classifier: License :: OSI Approved :: GNU Affero General Public License v3
Classifier: Operating System :: OS Independent
Requires-Python: >=3.6
